{"data":[{"word":"by","state":"prep","def":"အားျဖင့္"},{"word":"by  the back door","state":"idm","def":"ေနာက္ေဖးေပါက္ မွ။"},{"word":"by / from the look of sb / sth","state":"idm","def":"ၾကည့္ရတာေတာ႔။ ပံုေပါက္တယ္။ ၾကည့္ရႈေစာင့္ေရွာက္ သည္။ သိတတ္သည္။"},{"word":"by a long way","state":"idm","def":"ေအးေအးေလး။ အသာေလး။"},{"word":"by accident","state":"idm","def":"မေတာ္တဆ။"},{"word":"by all means","state":"idm","def":"လုပ္ခြင့္ျပဳသည့္အခါမ်ိဳး၌သံုးေလ့ရိွသည့္စကား။ ရပါတယ္။"},{"word":"by choice","state":"idm","def":"ေရြးခ်ယ္မႈအရ။"},{"word":"by degrees","state":"idm","def":"တစ္ဆင့္ျပီးတစ္ဆင့္။ တစ္စတစ္စ။"},{"word":"by dint of sth","state":"idm","def":"အေၾကာင္း(ျဖင့္)။"},{"word":"by heart","state":"idm","def":"အာဂံု။အလြတ္။"},{"word":"by inches","state":"idm","def":"သီသီကေလး။"},{"word":"by itself","state":"idm","def":"အလိုအေလ်ာက္။ တစ္ခုတည္း။ သီးျခား။ သီးသန္႔။"},{"word":"by lot","state":"idm","def":"မဲျဖင့္။"},{"word":"by means of sth","state":"idm","def":"အားျဖင့္။ ျဖင့္။"},{"word":"by mistake","state":"idm","def":"မွားျပီးေတာ႔။"},{"word":"by name","state":"idm","def":"နာမည္ႏွင့္တကြ။ I only know her by name .သူ႔ကို နာမည္သာ ၾကားဖူးပါတယ္။"},{"word":"by nmeans; not by any (manner of) means","state":"idm","def":"လံုးဝ။ နည္းနည္းမွ်။ မည္သည့္နည္းႏွင့္မွ်။"},{"word":"by numbers","state":"IDM(infml)","def":"နံပါတ္စဉ္အတိုင္း ။ နံပါတ္အလိုက္ ။"},{"word":"by one's  own  account","state":"idm","def":"ျပန္လည္ေျပာဆိုခ်က္ အရ။ အေျပာအရ။"},{"word":"by the way","state":"idm","def":"စကားမစပ္။"},{"word":"by/ of the name of","state":"idm","def":"အမည္ရိွ။"},{"word":"by/in comparison","state":"idm","def":"နိႈင္းယွဉ္လိုက္ ရင္။ ယွဉ္ၾကည့္လိုက္ေတာ႔။ နိႈင္းယွဉ္လို႔မရဘူး။ တျခားစီပဲ။"},
]}