{"data":[{"word":"via","state":"prep","def":"မွတစ္ဆင့္ျဖင့္"},{"word":"victim","state":"n","def":"ဒုကၡသည္"},{"word":"victims","state":"n[pl]","def":"ဒုကၡသည္"},{"word":"victories","state":"n[pl]","def":"ဒုကၡသည္"},{"word":"victory","state":"n","def":"ေအာင္ျမင္ျခင္း"},{"word":"video","state":"n","def":"ဗီဒီယိုရိုက္ကူးျပသမုစနစ္"},{"word":"video store","state":"n","def":"ဗီြဒီယိုဆိုင္"},{"word":"videos","state":"n[pl]","def":"ဗီဒီယိုတိပ္ေခြ"},{"word":"view","state":"n","def":"ျမင္ကြင္း"},{"word":"view","state":"v","def":"ယူဆ"},{"word":"viewed","state":"v[pt]","def":"ယူဆ"},{"word":"viewed","state":"v[pp]","def":"ယူဆ"},{"word":"viewer","state":"n","def":"ၾကည့္ရုသူ"},{"word":"viewers","state":"n[pl]","def":"ၾကည့္ရုသူ"},{"word":"viewing","state":"v[ing]","def":"ယူဆ"},{"word":"views","state":"n[pl]","def":"ျမင္ကြင္း"},{"word":"views","state":"v[sg]","def":"ယူဆ"},{"word":"vigin","state":"v","def":"အပ်ိဳစင္"},{"word":"vigorous","state":"adj","def":"ၾကံခိုင္ေသာ။ ျဖတ္လတ္ေသာ။ ဥာဏ္ၾကီးေသာ။"},{"word":"village","state":"n","def":"ရြာ"},{"word":"villager","state":"n","def":"ရြာသူ၊ရြာသား။"},{"word":"villages","state":"n[pl]","def":"ရြာ"},{"word":"vindicate","state":"v","def":"သက္ေသထူ"},{"word":"vindicated","state":"v[pt]","def":"သက္ေသထူ"},{"word":"vindicated","state":"v[pp]","def":"သက္ေသထူ"},{"word":"vindicates","state":"v[sg]","def":"သက္ေသထူ"},{"word":"vindicating","state":"v[ing]","def":"သက္ေသထူ"},{"word":"vines","state":"n","def":"ႏြယ္ပင္မ်ား"},{"word":"vintner","state":"n","def":"ဝိုက္အရာက္ေရာင္းခ်သဴ"},{"word":"vinyl","state":"adj","def":"ဓာတုပစၥည္းမ်ားပါဝင္ေသာ၊ ဓာတုနည္းျဖင့္ျပဳလုပ္ထားေသာ"},{"word":"viola","state":"n","def":"တေယာအလတ္"},{"word":"violas","state":"n[pl]","def":"တေယာအလတ္"},{"word":"violate","state":"n","def":"စာခ်ဳပ္ခ်ိဳးေဖာက္သည္"},{"word":"violated","state":"v[pt]","def":"ခ်ိဳးေဖာက္"},{"word":"violated","state":"v[pp]","def":"ခ်ိဳးေဖာက္"},{"word":"violates","state":"v[sg]","def":"ခ်ိဳးေဖာက္"},{"word":"violating","state":"v[ing]","def":"ခ်ိဳးေဖာက္"},{"word":"violence","state":"n","def":"အၾကမ္းဖက္မု"},{"word":"violent","state":"adj","def":"ၾကမ္းၾကဳတ္"},{"word":"violent wind","state":"n","def":"ေလနီၾကမ္း"},{"word":"violently","state":"adv","def":"ျပင္းျပင္းထန္ထန္"},{"word":"violet","state":"n","def":"ခရမ္းရင့္ေရာင္"},{"word":"violets","state":"n[pl]","def":"ခရမ္းရင့္ေရာင္"},{"word":"violin","state":"n","def":"တေယာ"},{"word":"violins","state":"n[pl]","def":"တေယာ"},{"word":"viper","state":"n","def":"ေျမြေပြး"},{"word":"vipers","state":"n[pl]","def":"ေျမြေပြး"},{"word":"virgin","state":"n","def":"အပ်ိဳ"},{"word":"virgins","state":"n[pl]","def":"အပ်ိဳ"},{"word":"Virgo","state":"n","def":"ကန္"},{"word":"virtually","state":"adv","def":"လုနီးပါး"},{"word":"virtue","state":"n","def":"သူေတာ္ေကာင္းတရား"},{"word":"virtues","state":"n[pl]","def":"သူေတာ္ေကာင္းတရား"},{"word":"virus","state":"n","def":"ေရာဂါပိုးမႊား"},{"word":"viruses","state":"n[pl]","def":"ေရာဂါပိုးမႊား"},{"word":"visible","state":"adj","def":"ျမင္ႏိုင္"},{"word":"vision","state":"n","def":"အျမင္"},{"word":"visionary","state":"adj","def":"အေျမာ္အျမင္ ရိွေသာ။ စိတ္ကူးဉာဏ္ ျမင့္မားေသာ၊ ထက္ျမက္ေသာ။"},{"word":"visioned","state":"v[pt]","def":"ျမင္ခဲ့"},{"word":"visioned","state":"v[pp]","def":"ျမင္ခဲ့ျပီး"},{"word":"visioning","state":"v[ing]","def":"ျမင္ျခင္း။"},{"word":"visions","state":"n[pl]","def":"အျမင္"},{"word":"visions","state":"v[sg]","def":"ျမင္သည္။"},{"word":"visit","state":"v","def":"အလည္အပတ္သြား"},{"word":"visit","state":"n","def":"လည္ပတ္ျခင္း"},{"word":"visited","state":"v[pt]","def":"အလည္အပတ္သြား"},{"word":"visited","state":"v[pp]","def":"အလည္အပတ္သြား"},{"word":"visiting","state":"v[ing]","def":"အလည္အပတ္သြား"},{"word":"visitor","state":"n","def":"ဧည့္သည္"},{"word":"visitors","state":"n[pl]","def":"ဧည့္သည္"},{"word":"visits","state":"n[pl]","def":"လည္ပတ္ျခင္း"},{"word":"visits","state":"v[sg]","def":"လည္ပတ္သည္"},{"word":"visual","state":"adj","def":"စကၡဳအာရံု"},{"word":"visual","state":"n","def":"ပံု၊ ဓာတ္ပံုစသည္"},{"word":"vital","state":"adj","def":"မရိွမျဖစ္လိုအပ္"},{"word":"viva voce","state":"n","def":"ႏုတ္ေျဖစာေမးပဲြ။"},
]}